java_module_dependencies_viewer/__init__.py
java_module_dependencies_viewer/show_java_module_dependencies.py
java_module_dependencies_viewer-0.0.2.dist-info/LICENSE
java_module_dependencies_viewer-0.0.2.dist-info/METADATA
java_module_dependencies_viewer-0.0.2.dist-info/WHEEL
java_module_dependencies_viewer-0.0.2.dist-info/top_level.txt
java_module_dependencies_viewer-0.0.2.dist-info/RECORD
