Metadata-Version: 2.1
Name: java_module_dependencies_viewer
Version: 0.0.2
Summary: Tool to create or show a diagram representing the dependencies declared in a set of module-info.java files.
Author-email: MKO575 <mko575@duck.com>
Project-URL: Homepage, https://gitlab.com/mko-utilities/java-module-dependencies-viewer
Project-URL: Bug Tracker, https://gitlab.com/mko-utilities/java-module-dependencies-viewer/-/issues
Classifier: Development Status :: 4 - Beta
Classifier: License :: OSI Approved :: CEA CNRS Inria Logiciel Libre License, version 2.1 (CeCILL-2.1)
Classifier: Operating System :: OS Independent
Classifier: Programming Language :: Python :: 3
Classifier: Environment :: Console
Classifier: Intended Audience :: Developers
Classifier: Topic :: Scientific/Engineering :: Visualization
Classifier: Topic :: Software Development :: Documentation
Classifier: Topic :: Software Development :: Libraries :: Java Libraries
Classifier: Topic :: Utilities
Requires-Python: >=3.7
License-File: LICENSE
